typer_group_prefix/__init__.py
typer_group_prefix/parsers.py
typer_group_prefix/py.typed
typer_group_prefix-0.1.11.dist-info/METADATA
typer_group_prefix-0.1.11.dist-info/WHEEL
typer_group_prefix-0.1.11.dist-info/licenses/LICENSE
typer_group_prefix-0.1.11.dist-info/RECORD
