Metadata-Version: 2.4
Name: typer-group-prefix
Version: 0.1.11
Summary: Add Prefixes to Typer Groups
Project-URL: Homepage, https://github.com/KalleDK/py-typer-group-prefix
Project-URL: Documentation, https://github.com/KalleDK/py-typer-group-prefix
Project-URL: Repository, https://github.com/KalleDK/py-typer-group-prefix.git
Author-email: Kalle Aagaard <git@k-moeller.dk>
Maintainer-email: Kalle Aagaard <git@k-moeller.dk>
License-File: LICENSE
Classifier: License :: OSI Approved :: MIT License
Classifier: Programming Language :: Python :: 3.11
Requires-Python: >=3.11
Requires-Dist: typer-di>=0.1.3
Requires-Dist: typer-slim>=0.17.4
